.DS_Store
arrpy/__init__.py
arrpy/_basicrows.py
arrpy/_checks.py
arrpy/checks.py
arrpy/listprocessor.py
arrpy-1.0.0.dist-info/LICENSE
arrpy-1.0.0.dist-info/METADATA
arrpy-1.0.0.dist-info/WHEEL
arrpy-1.0.0.dist-info/top_level.txt
arrpy-1.0.0.dist-info/RECORD
