Metadata-Version: 2.1
Name: arrpy
Version: 1.0.0
Summary: arrpy is a 2D array manipulation module
Home-page: https://github.com/meemrich/arrpy
Author: Mehera Emrich
License: UNKNOWN
Project-URL: Bug Tracker, https://github.com/meemrich/arrpy/issues
Platform: UNKNOWN
Classifier: Programming Language :: Python :: 3
Classifier: License :: OSI Approved :: Mozilla Public License 2.0 (MPL 2.0)
Classifier: Operating System :: OS Independent
Requires-Python: >=3
